jsonschema_autodoc/__init__.py
jsonschema_autodoc/document.py
jsonschema_autodoc/meta.py
jsonschema_autodoc/protocol.py
jsonschema_autodoc/registry.py
jsonschema_autodoc/schema.py
jsonschema_autodoc/sphinx.py
jsonschema_autodoc/page/__init__.py
jsonschema_autodoc/page/default.py
jsonschema_autodoc-0.1.0.dist-info/METADATA
jsonschema_autodoc-0.1.0.dist-info/WHEEL
jsonschema_autodoc-0.1.0.dist-info/top_level.txt
jsonschema_autodoc-0.1.0.dist-info/RECORD
